bxsolana_trader_proto/__init__.py
bxsolana_trader_proto/api.py
bxsolana_trader_proto/common.py
bxsolana_trader_proto/packet.py
bxsolana_trader_proto/api/__init__.py
bxsolana_trader_proto/common/__init__.py
bxsolana_trader_proto/google/__init__.py
bxsolana_trader_proto/google/api.py
bxsolana_trader_proto/google/api/__init__.py
bxsolana_trader_proto/grpc/__init__.py
bxsolana_trader_proto/grpc/gateway/__init__.py
bxsolana_trader_proto/grpc/gateway/protoc_gen_openapiv2/__init__.py
bxsolana_trader_proto/grpc/gateway/protoc_gen_openapiv2/options.py
bxsolana_trader_proto/grpc/gateway/protoc_gen_openapiv2/options/__init__.py
bxsolana_trader_proto-0.1.9.dist-info/METADATA
bxsolana_trader_proto-0.1.9.dist-info/WHEEL
bxsolana_trader_proto-0.1.9.dist-info/top_level.txt
bxsolana_trader_proto-0.1.9.dist-info/RECORD
