Metadata-Version: 2.4
Name: bxsolana-trader-proto
Version: 0.1.9
Summary: proto-generated files for solana-trader-api
Requires-Dist: betterproto==v2.0.0b6
